parsesafe/__init__.py
parsesafe/advancer.py
parsesafe/combinators.py
parsesafe/err.py
parsesafe-0.1.2.dist-info/licenses/LICENSE
parsesafe-0.1.2.dist-info/METADATA
parsesafe-0.1.2.dist-info/WHEEL
parsesafe-0.1.2.dist-info/top_level.txt
parsesafe-0.1.2.dist-info/RECORD
