Metadata-Version: 2.4
Name: parsesafe
Version: 0.1.2
Summary: A type-safe parsing combinator library.
Requires-Python: >=3.14
License-File: LICENSE
Dynamic: license-file
